__init__.py
cachr/__init__.py
cachr/caches.py
cachr/policies/__init__.py
cachr/policies/cache_eviction_policy.py
cachr/policies/cache_strategy.py
cachr/policies/lfu_eviction_policy.py
cachr/policies/lru_eviction_policy.py
cachr/policies/random_eviction_policy.py
cachr/policies/sliding_window_eviction_policy.py
cachr/policies/ttl_eviction_policy.py
cachr-0.0.9.dist-info/METADATA
cachr-0.0.9.dist-info/WHEEL
cachr-0.0.9.dist-info/top_level.txt
cachr-0.0.9.dist-info/RECORD
