Metadata-Version: 2.1
Name: cachr
Version: 0.0.9
Summary: Easy caching in Python. Cachr allows you to compose your own cache and comes pre-packaged with many useful caches
Author-email: Mike Huls <mikehuls42@gmail.com>
Project-URL: Homepage, https://github.com/mike-huls/cachr
Project-URL: Bug Tracker, https://github.com/mike-huls/cachr/issues
Project-URL: Documentation, https://github.com/mike-huls/cachr/blob/master/README.md/
Project-URL: Changelog, https://github.com/mike-huls/cachr/blob/master/CHANGELOG.md/
Project-URL: Source, https://github.com/mike-huls/cachr/
Project-URL: Say Thanks!, https://www.buymeacoffee.com/mikehuls
Keywords: caching,cache
Classifier: Development Status :: 5 - Production/Stable
Classifier: Intended Audience :: Developers
Classifier: Intended Audience :: Information Technology
Classifier: Intended Audience :: System Administrators
Classifier: Operating System :: OS Independent
Classifier: License :: OSI Approved :: MIT License
Classifier: Topic :: Software Development :: Libraries :: Python Modules
Classifier: Topic :: Software Development :: Libraries
Classifier: Topic :: Software Development
Classifier: Programming Language :: Python
Classifier: Programming Language :: Python :: 3
Classifier: Programming Language :: Python :: 3 :: Only
Classifier: Programming Language :: Python :: 3.9
Classifier: Programming Language :: Python :: 3.10
Classifier: Programming Language :: Python :: 3.11
Classifier: Programming Language :: Python :: 3.12
Classifier: Programming Language :: Python :: 3.13
Classifier: Programming Language :: Python :: Implementation :: CPython
Classifier: License :: OSI Approved :: MIT License
Requires-Python: >=3.9
